epiccakeking_journal/__init__.py
epiccakeking_journal/__main__.py
epiccakeking_journal/backend.py
epiccakeking_journal/modals.py
epiccakeking_journal/utilities.py
epiccakeking_journal/widgets.py
epiccakeking_journal/css/main.css
epiccakeking_journal/ui/AltGui.ui
epiccakeking_journal/ui/JournalPage.ui
epiccakeking_journal/ui/MainWindow.ui
epiccakeking_journal/ui/SearchModal.ui
epiccakeking_journal/ui/SearchResult.ui
epiccakeking_journal/ui/SettingsModal.ui
epiccakeking_journal-0.0.3.data/data/share/applications/io.github.epiccakeking.Journal.desktop
epiccakeking_journal-0.0.3.data/data/share/icons/io.github.epiccakeking.Journal.svg
epiccakeking_journal-0.0.3.dist-info/COPYING
epiccakeking_journal-0.0.3.dist-info/METADATA
epiccakeking_journal-0.0.3.dist-info/WHEEL
epiccakeking_journal-0.0.3.dist-info/top_level.txt
epiccakeking_journal-0.0.3.dist-info/RECORD
